langchainforhcx/__init__.py
langchainforhcx/base_language.py
langchainforhcx/cache.py
langchainforhcx/env.py
langchainforhcx/example_generator.py
langchainforhcx/formatting.py
langchainforhcx/hub.py
langchainforhcx/input.py
langchainforhcx/model_laboratory.py
langchainforhcx/py.typed
langchainforhcx/python.py
langchainforhcx/requests.py
langchainforhcx/serpapi.py
langchainforhcx/sql_database.py
langchainforhcx/text_splitter.py
langchainforhcx/_api/__init__.py
langchainforhcx/_api/deprecation.py
langchainforhcx/_api/path.py
langchainforhcx/adapters/__init__.py
langchainforhcx/adapters/openai.py
langchainforhcx/agents/__init__.py
langchainforhcx/agents/agent.py
langchainforhcx/agents/agent_iterator.py
langchainforhcx/agents/agent_types.py
langchainforhcx/agents/initialize.py
langchainforhcx/agents/load_tools.py
langchainforhcx/agents/loading.py
langchainforhcx/agents/schema.py
langchainforhcx/agents/tools.py
langchainforhcx/agents/types.py
langchainforhcx/agents/utils.py
langchainforhcx/agents/agent_toolkits/__init__.py
langchainforhcx/agents/agent_toolkits/azure_cognitive_services.py
langchainforhcx/agents/agent_toolkits/base.py
langchainforhcx/agents/agent_toolkits/ainetwork/__init__.py
langchainforhcx/agents/agent_toolkits/ainetwork/toolkit.py
langchainforhcx/agents/agent_toolkits/clickup/__init__.py
langchainforhcx/agents/agent_toolkits/clickup/toolkit.py
langchainforhcx/agents/agent_toolkits/conversational_retrieval/__init__.py
langchainforhcx/agents/agent_toolkits/conversational_retrieval/openai_functions.py
langchainforhcx/agents/agent_toolkits/conversational_retrieval/tool.py
langchainforhcx/agents/agent_toolkits/csv/__init__.py
langchainforhcx/agents/agent_toolkits/file_management/__init__.py
langchainforhcx/agents/agent_toolkits/file_management/toolkit.py
langchainforhcx/agents/agent_toolkits/github/__init__.py
langchainforhcx/agents/agent_toolkits/github/toolkit.py
langchainforhcx/agents/agent_toolkits/gitlab/__init__.py
langchainforhcx-0.0.1.dist-info/METADATA
langchainforhcx-0.0.1.dist-info/WHEEL
langchainforhcx-0.0.1.dist-info/top_level.txt
langchainforhcx-0.0.1.dist-info/RECORD
